athanasius/__init__.py
athanasius/archiver.py
athanasius/cli.py
athanasius/extractor.py
athanasius/utils.py
athanasius-0.1.2.dist-info/LICENSE
athanasius-0.1.2.dist-info/METADATA
athanasius-0.1.2.dist-info/WHEEL
athanasius-0.1.2.dist-info/entry_points.txt
athanasius-0.1.2.dist-info/top_level.txt
athanasius-0.1.2.dist-info/RECORD
